gnews/__init__.py
gnews/api_client.py
gnews/client_builder.py
gnews/enums.py
gnews/exceptions.py
gnews/response_handler.py
gnews/retrier.py
gnewsio-0.1.6.dist-info/LICENSE
gnewsio-0.1.6.dist-info/METADATA
gnewsio-0.1.6.dist-info/WHEEL
gnewsio-0.1.6.dist-info/top_level.txt
gnewsio-0.1.6.dist-info/RECORD
