Metadata-Version: 2.1
Name: gnewsio
Version: 0.1.6
Summary: A Python client for the GNews API with category, country, and language filtering
Home-page: https://github.com/project-arth-tech/gnewsio
Author: Sanket Mishra
Author-email: isanketmishra@gmail.com
Classifier: Programming Language :: Python :: 3
Classifier: License :: OSI Approved :: MIT License
Classifier: Operating System :: OS Independent
Requires-Python: >=3.9
License-File: LICENSE
Requires-Dist: requests
